cordic.vhd
library ieee;
use ieee.std_logic_1164.all;
use ieee.numeric_std.all;

entity cordic is port (
   CLK   : in std_logic;
   RST   : in std_logic;
   PHI   : in signed(15 downto 0);
   N     : in natural range 0 to 16;
   START : in std_logic;
   R1    : out signed(15 downto 0);
   R2    : out signed(15 downto 0);
   RDY   : out std_logic);
end entity;

architecture RTL of cordic is

   function fp2fix(x: real; M: real) return signed is
   begin
      return to_signed(integer(x*M),16);
   end;
        
   function fix2fp(x: signed(15 downto 0); M: real) return real is
   begin
      return real(to_integer(x))/M;
   end;

   type t_state is (Repos,Calcul);
   signal etat : t_state;

   type t_coef is array(0 to 15) of signed(15 downto 0);
   signal THETA : t_coef := ( 
      to_signed(12150,16), to_signed(7172,16), 
      to_signed(3789,16), to_signed(1923,16), 
      to_signed(965,16), to_signed(483,16), 
      to_signed(241,16), to_signed(120,16), 
      to_signed(60,16), to_signed(30,16), 
      to_signed(15,16), to_signed(7,16), 
      to_signed(3,16), to_signed(1,16), 
      to_signed(0,16), to_signed(0,16));
   signal A : t_coef := (
      to_signed(22627,16),to_signed(20238,16),
      to_signed(19634,16),to_signed(19482,16),
      to_signed(19444,16),to_signed(19435,16),
      to_signed(19432,16),to_signed(19432,16),
      to_signed(19432,16),to_signed(19432,16),
      to_signed(19432,16),to_signed(19432,16),
      to_signed(19432,16),to_signed(19432,16),
      to_signed(19432,16),to_signed(19432,16));

   signal i : natural range 0 to 16;
   signal alpha,x1,y1 : signed(15 downto 0);

begin
   process (CLK,RST)
   begin
      if RST ='1' then 
         etat <= Repos;
         RDY <= '1';
      elsif rising_edge(CLK) then
         case etat is
            when Repos =>
               if START = '1' then
                  RDY <= '0';
                  x1 <= A(N-1);
                  y1 <= to_signed(0,16);
                  alpha <= to_signed(0,16);
                  i <= 0;
                  etat <= Calcul;
               end if;
            
            when Calcul =>
                  if (i < N) then
                     if (alpha < phi) then
                        x1 <= x1 - shift_right(y1, i);
                        y1 <= y1 + shift_right(x1, i);
                        alpha <= alpha + THETA(i);
                     else 
                        x1 <= x1 + shift_right(y1, i);
                        y1 <= y1 - shift_right(x1, i);
                        alpha <= alpha - THETA(i);
                     end if;
                     i <= i + 1;
                        
                  else
                     RDY <= '1';
                     R1 <= x1;
                     R2 <= y1;
                     etat <= Repos;
                  end if;
         end case;
      end if;
   end process;
end architecture;

tb.vhd
library ieee;
use ieee.std_logic_1164.all;
use ieee.numeric_std.all;

entity tb is
end tb;

architecture seq of tb is

	signal CLK  : std_logic;
  signal RST  : std_logic;
	signal PHI  : signed(15 downto 0);
	signal N    : natural range 0 to 16;
	signal START: std_logic;
  signal R1   : signed(15 downto 0);
  signal R2   : signed(15 downto 0);
  signal RDY  : std_logic;

begin

  UUT: entity work.cordic port map(CLK,RST,PHI,N,START,R1,R2,RDY);

  CLOCK: process
  begin
    CLK <= '1';
    wait for 5 ns;
    CLK <= '0';
    wait for 5 ns;
    end process;

  INITIALISATION: process
  begin
    PHI <= to_signed(60*270,16);
    N <= 16;
    wait for 50 ns;
    START <= '1';
    wait for 10 ns;
    START <= '0';
    wait ;
  end process;
  
  RAZ: process
  begin
    RST <= '1';
    wait for 10 ns;
    RST <= '0';
    wait;
  end process;

end architecture;

VHDL/tb.vcd
$date
  Tue Mar 22 16:55:04 2022
$end
$version
  GHDL v0
$end
$timescale
  1 fs
$end
$scope module standard $end
$upscope $end
$scope module std_logic_1164 $end
$upscope $end
$scope module numeric_std $end
$upscope $end
$scope module tb $end
$var reg 1 ! clk $end
$var reg 1 " rst $end
$var reg 16 # phi[15:0] $end
$var integer 32 $ n $end
$var reg 1 % start $end
$var reg 16 & r1[15:0] $end
$var reg 16 ' r2[15:0] $end
$var reg 1 ( rdy $end
$scope module uut $end
$var reg 1 ) clk $end
$var reg 1 * rst $end
$var reg 16 + phi[15:0] $end
$var integer 32 , n $end
$var reg 1 - start $end
$var reg 16 . r1[15:0] $end
$var reg 16 / r2[15:0] $end
$var reg 1 0 rdy $end
$comment etat is not handled $end
$comment theta is not handled $end
$comment a is not handled $end
$var integer 32 1 i $end
$var reg 16 2 alpha[15:0] $end
$var reg 16 3 x1[15:0] $end
$var reg 16 4 y1[15:0] $end
$upscope $end
$upscope $end
$enddefinitions $end
#0
1!
1"
b0011111101001000 #
b10000 $
U%
bUUUUUUUUUUUUUUUU &
bUUUUUUUUUUUUUUUU '
1(
1)
1*
b0011111101001000 +
b10000 ,
U-
bUUUUUUUUUUUUUUUU .
bUUUUUUUUUUUUUUUU /
10
b0 1
bUUUUUUUUUUUUUUUU 2
bUUUUUUUUUUUUUUUU 3
bUUUUUUUUUUUUUUUU 4
#5000000
0!
0)
#10000000
1!
0"
1)
0*
#15000000
0!
0)
#20000000
1!
1)
#25000000
0!
0)
#30000000
1!
1)
#35000000
0!
0)
#40000000
1!
1)
#45000000
0!
0)
#50000000
1!
1%
0(
1)
1-
00
b0000000000000000 2
b0100101111101000 3
b0000000000000000 4
#55000000
0!
0)
#60000000
1!
0%
1)
0-
b1 1
b0010111101110110 2
b0100101111101000 4
#65000000
0!
0)
#70000000
1!
1)
b10 1
b0100101101111010 2
b0010010111110100 3
b0111000111011100 4
#75000000
0!
0)
#80000000
1!
1)
b11 1
b0011110010101101 2
b0100001001101011 3
b0110100001011111 4
#85000000
0!
0)
#90000000
1!
1)
b100 1
b0100010000110000 2
b0011010101100000 3
b0111000010101100 4
#95000000
0!
0)
#100000000
1!
1)
b101 1
b0100000001101011 2
b0011110001101010 3
b0110110101010110 4
#105000000
0!
0)
#110000000
1!
1)
b110 1
b0011111010001000 2
b0011111111010100 3
b0110101101110011 4
#115000000
0!
0)
#120000000
1!
1)
b111 1
b0011111101111001 2
b0011111000100111 3
b0110110001110010 4
#125000000
0!
0)
#130000000
1!
1)
b1000 1
b0011111100000001 2
b0011111011111111 3
b0110101111110110 4
#135000000
0!
0)
#140000000
1!
1)
b1001 1
b0011111100111101 2
b0011111010010100 3
b0110110000110100 4
#145000000
0!
0)
#150000000
1!
1)
b1010 1
b0011111101011011 2
b0011111001011110 3
b0110110001010011 4
#155000000
0!
0)
#160000000
1!
1)
b1011 1
b0011111101001100 2
b0011111001111001 3
b0110110001000100 4
#165000000
0!
0)
#170000000
1!
1)
b1100 1
b0011111101000101 2
b0011111010000110 3
b0110110000111101 4
#175000000
0!
0)
#180000000
1!
1)
b1101 1
b0011111101001000 2
b0011111010000000 3
b0110110001000000 4
#185000000
0!
0)
#190000000
1!
1)
b1110 1
b0011111101000111 2
b0011111010000011 3
b0110110000111111 4
#195000000
0!
0)
#200000000
1!
1)
b1111 1
b0011111010000010 3
#205000000
0!
0)
#210000000
1!
1)
b10000 1
#215000000
0!
0)
#220000000
1!
b0011111010000010 &
b0110110000111111 '
1(
1)
b0011111010000010 .
b0110110000111111 /
10
